geometryobject.py
geometryobject2d.py
geometryobject-1.0.dist-info/METADATA
geometryobject-1.0.dist-info/WHEEL
geometryobject-1.0.dist-info/top_level.txt
geometryobject-1.0.dist-info/RECORD
