Metadata-Version: 2.1
Name: geometryobject
Version: 1.0
Summary: Aplication program to print some 2d geometry object
Home-page: https://github.com/samuelliem
Author: samuelliem
Author-email: samuelliem99@gmail.com
License: UNKNOWN
Platform: UNKNOWN
